simple_iot_device/__init__.py
simple_iot_device/device/__init__.py
simple_iot_device/device/simple_iot_device.py
simple_iot_device/device/utils/__init__.py
simple_iot_device/device/utils/utils.py
simple_iot_device/prototype/__init__.py
simple_iot_device/prototype/iot.py
simple_iot_device-1.0.1.dist-info/LICENSE
simple_iot_device-1.0.1.dist-info/METADATA
simple_iot_device-1.0.1.dist-info/WHEEL
simple_iot_device-1.0.1.dist-info/top_level.txt
simple_iot_device-1.0.1.dist-info/RECORD
