Metadata-Version: 2.1
Name: simple-iot-device
Version: 1.0.1
Summary: Simple IOT device simulator
Author-email: alv2017 <alv2017@protonmail.com>
License: MIT License (MIT)
Project-URL: Homepage, https://github.com/alv2017/simple-iot-device/
Keywords: iot,measurements,simulator
Classifier: License :: OSI Approved :: MIT License
Classifier: Programming Language :: Python
Classifier: Programming Language :: Python :: 3.9
Classifier: Programming Language :: Python :: 3.10
Classifier: Programming Language :: Python :: 3.11
Requires-Python: >=3.9
License-File: LICENSE
Provides-Extra: dev
Requires-Dist: black ; extra == 'dev'
Requires-Dist: flake8 ; extra == 'dev'
Requires-Dist: isort ; extra == 'dev'
Requires-Dist: pytest ; extra == 'dev'
